eventipy/__init__.py
eventipy/event.py
eventipy/event_handler.py
eventipy/event_stream.py
eventipy-2.1.1.dist-info/LICENSE.md
eventipy-2.1.1.dist-info/WHEEL
eventipy-2.1.1.dist-info/METADATA
eventipy-2.1.1.dist-info/RECORD
