Metadata-Version: 2.1
Name: eventipy
Version: 2.1.1
Summary: In-memory python event library
License: MIT
Author: Jonatan Martens
Author-email: jonatanmartenstav@gmail.com
Requires-Python: >=3.6.2,<4.0.0
Classifier: License :: OSI Approved :: MIT License
Classifier: Programming Language :: Python :: 3
Classifier: Programming Language :: Python :: 3.7
Classifier: Programming Language :: Python :: 3.8
Classifier: Programming Language :: Python :: 3.9
Requires-Dist: pydantic (==1.8.2)
